srmd_ncnn_py-2.0.0.dist-info/METADATA
srmd_ncnn_py-2.0.0.dist-info/WHEEL
srmd_ncnn_py-2.0.0.dist-info/licenses/LICENSE
srmd_ncnn_py/__init__.py
srmd_ncnn_py/models/models-srmd/srmd_x2.bin
srmd_ncnn_py/models/models-srmd/srmd_x2.param
srmd_ncnn_py/models/models-srmd/srmd_x3.bin
srmd_ncnn_py/models/models-srmd/srmd_x3.param
srmd_ncnn_py/models/models-srmd/srmd_x4.bin
srmd_ncnn_py/models/models-srmd/srmd_x4.param
srmd_ncnn_py/models/models-srmd/srmdnf_x2.bin
srmd_ncnn_py/models/models-srmd/srmdnf_x2.param
srmd_ncnn_py/models/models-srmd/srmdnf_x3.bin
srmd_ncnn_py/models/models-srmd/srmdnf_x3.param
srmd_ncnn_py/models/models-srmd/srmdnf_x4.bin
srmd_ncnn_py/models/models-srmd/srmdnf_x4.param
srmd_ncnn_py/srmd_ncnn_vulkan.py
srmd_ncnn_py/srmd_ncnn_vulkan_wrapper.cpython-311-darwin.so
srmd_ncnn_py-2.0.0.dist-info/RECORD
